test_publish_mcp/__init__.py
test_publish_mcp-0.1.0.dist-info/METADATA
test_publish_mcp-0.1.0.dist-info/WHEEL
test_publish_mcp-0.1.0.dist-info/entry_points.txt
test_publish_mcp-0.1.0.dist-info/RECORD
