Metadata-Version: 2.4
Name: test-publish-mcp
Version: 0.1.0
Summary: Add your description here
Author-email: XDY <examle@examle.com>
Requires-Python: >=3.13
Requires-Dist: httpx>=0.28.1
Requires-Dist: mcp[cli]>=1.11.0
Requires-Dist: openai>=1.95.0
Requires-Dist: python-dotenv>=1.1.1
